pycounts_Abhiket/__init__.py
pycounts_Abhiket/plotting.py
pycounts_Abhiket/pycounts_Abhiket.py
pycounts_abhiket-0.1.0.dist-info/LICENSE
pycounts_abhiket-0.1.0.dist-info/WHEEL
pycounts_abhiket-0.1.0.dist-info/METADATA
pycounts_abhiket-0.1.0.dist-info/RECORD
